lmnr_baml-0.40.1.dist-info/METADATA
lmnr_baml-0.40.1.dist-info/WHEEL
lmnr_baml-0.40.1.dist-info/entry_points.txt
lmnr_baml/__init__.py
lmnr_baml/lmnr_baml.pypy38-pp73-aarch64-linux-gnu.so
lmnr_baml-0.40.1.dist-info/RECORD
