Metadata-Version: 2.3
Name: lmnr_baml
Version: 0.40.1
Summary: LMNR BAML for Python
Author: Boundary <contact@boundaryml.com>
Author-email: Boundary <contact@boundaryml.com>
